magicsandbox_streaming/__init__.py
magicsandbox_streaming/length_prefix_transform.py
magicsandbox_streaming-0.1.0.dist-info/licenses/LICENSE
magicsandbox_streaming-0.1.0.dist-info/WHEEL
magicsandbox_streaming-0.1.0.dist-info/METADATA
magicsandbox_streaming-0.1.0.dist-info/RECORD
