Metadata-Version: 2.4
Name: magicsandbox-streaming
Version: 0.1.0
Summary: Streaming utilities for Magic Sandbox
Requires-Python: >=3.7
License-File: LICENSE
Project-URL: Homepage, https://github.com/magicsandbox-ai/magicsandbox
